Metadata-Version: 1.0
Name: sysperf
Version: 0.0.5
Summary: System performance dashboard showing real time cpu, memory, swap, disk and network performance metrics
Home-page: https://github.com/yogeshsd/sysperf
Author: Yogesh Deshpande
Author-email: yogeshsd@gmail.com
License: UNKNOWN
Platform: UNKNOWN
